<?xml version="1.0" encoding="UTF-8"?><record_update>
    <sys_choice action="INSERT_OR_UPDATE" field="disk_name" table="var__m_sys_hub_action_input_45de82a5dbfa00103dbef35eae9619de" version="3">
        <sys_choice action="INSERT_OR_UPDATE">
            <dependent_value/>
            <element>disk_name</element>
            <hint/>
            <inactive>false</inactive>
            <label>DISK1</label>
            <language>en</language>
            <name>var__m_sys_hub_action_input_45de82a5dbfa00103dbef35eae9619de</name>
            <sequence>0</sequence>
            <sys_created_by>admin</sys_created_by>
            <sys_created_on>2020-02-19 09:39:10</sys_created_on>
            <sys_domain>global</sys_domain>
            <sys_domain_path>/</sys_domain_path>
            <sys_id>8a4cf9b1dbc30010a16b5a75dc96199d</sys_id>
            <sys_mod_count>0</sys_mod_count>
            <sys_updated_by>admin</sys_updated_by>
            <sys_updated_on>2020-02-19 09:39:10</sys_updated_on>
            <value>disk1</value>
        </sys_choice>
        <sys_choice action="INSERT_OR_UPDATE">
            <dependent_value/>
            <element>disk_name</element>
            <hint/>
            <inactive>false</inactive>
            <label>-- None --</label>
            <language>en</language>
            <name>var__m_sys_hub_action_input_45de82a5dbfa00103dbef35eae9619de</name>
            <sequence>1</sequence>
            <sys_created_by>admin</sys_created_by>
            <sys_created_on>2020-02-19 09:37:22</sys_created_on>
            <sys_domain>global</sys_domain>
            <sys_domain_path>/</sys_domain_path>
            <sys_id>6fdbb5b1dbc30010a16b5a75dc961947</sys_id>
            <sys_mod_count>0</sys_mod_count>
            <sys_updated_by>admin</sys_updated_by>
            <sys_updated_on>2020-02-19 09:37:22</sys_updated_on>
            <value/>
        </sys_choice>
        <sys_choice action="INSERT_OR_UPDATE">
            <dependent_value/>
            <element>disk_name</element>
            <hint/>
            <inactive>false</inactive>
            <label>DISK2</label>
            <language>en</language>
            <name>var__m_sys_hub_action_input_45de82a5dbfa00103dbef35eae9619de</name>
            <sequence>1</sequence>
            <sys_created_by>admin</sys_created_by>
            <sys_created_on>2020-02-19 09:39:10</sys_created_on>
            <sys_domain>global</sys_domain>
            <sys_domain_path>/</sys_domain_path>
            <sys_id>464cf9b1dbc30010a16b5a75dc96199e</sys_id>
            <sys_mod_count>0</sys_mod_count>
            <sys_updated_by>admin</sys_updated_by>
            <sys_updated_on>2020-02-19 09:39:10</sys_updated_on>
            <value>disk2</value>
        </sys_choice>
        <sys_choice_set action="INSERT_OR_UPDATE">
            <element>disk_name</element>
            <name>var__m_sys_hub_action_input_45de82a5dbfa00103dbef35eae9619de</name>
            <sys_class_name>sys_choice_set</sys_class_name>
            <sys_created_by>admin</sys_created_by>
            <sys_created_on>2020-02-19 09:37:22</sys_created_on>
            <sys_id>a7dbb5b1dbc30010a16b5a75dc961948</sys_id>
            <sys_mod_count>0</sys_mod_count>
            <sys_name/>
            <sys_package display_value="Google Persistent Disk" source="sn_gpdisk_spoke">06a7f79ddb8b0010c5267bfdae9619b4</sys_package>
            <sys_policy/>
            <sys_scope display_value="Google Persistent Disk">06a7f79ddb8b0010c5267bfdae9619b4</sys_scope>
            <sys_update_name/>
            <sys_updated_by>admin</sys_updated_by>
            <sys_updated_on>2020-02-19 09:37:22</sys_updated_on>
        </sys_choice_set>
    </sys_choice>
</record_update>
